{"cameraMode":{"drawMode":0,"name":"Shaded","section":"Shading Mode"},"sceneLighting":true,"audioPlay":false,"sceneViewState":{"m_AlwaysRefresh":false,"showFog":true,"showSkybox":true,"showFlares":true,"showImageEffects":true,"showParticleSystems":true,"showVisualEffectGraphs":true,"m_FxEnabled":true},"in2DMode":false,"pivot":{"x":212.644287109375,"y":-7.547576427459717,"z":190.4622039794922},"rotation":{"x":-0.06618490070104599,"y":-0.9336434602737427,"z":0.24978357553482057,"w":-0.2489435225725174},"size":17.65784454345703,"orthographic":false}